custom_themes/__init__.py
custom_themes/colorschemes.py
custom_themes/custom_plotly_themes.py
CustomPlotlyThemes-0.1.0.dist-info/LICENSE
CustomPlotlyThemes-0.1.0.dist-info/METADATA
CustomPlotlyThemes-0.1.0.dist-info/WHEEL
CustomPlotlyThemes-0.1.0.dist-info/top_level.txt
CustomPlotlyThemes-0.1.0.dist-info/RECORD
