Metadata-Version: 2.1
Name: CustomPlotlyThemes
Version: 0.1.0
Summary: Custom themes for plotly
Home-page: https://gitlab.com/wime/CustomPlotlyThemes/
Author: Willem Meijer
Author-email: willem.meijer@mailbox.org
License: MIT
Keywords: plotly,themes
License-File: LICENSE
Requires-Dist: plotly
